{
  "query_terms": [
    "score",
    "end",
    "third",
    "quarter",
    "bristol",
    "central",
    "leading",
    "tied",
    "east",
    "catholic"
  ],
  "artifact_context": [
    {
      "artifact_id": "clip_120_00_180_00",
      "artifact_type": "clip",
      "relpath": "artifacts/0XB0BWhzNc/clips/clip_120_00_180_00.mp4",
      "time": {
        "clip": {
          "start_s": 120.0,
          "end_s": 126.0
        }
      },
      "contains": [
        "Bristol Central is leading E. CATHOLIC at the end of the third quarter.",
        "The visible score at the end of the third quarter is 52 to 40.",
        "Option A states Bristol Central is leading.",
        "Option C states East Catholic is leading.",
        "Option D states Bristol Central is leading.",
        "Option E states East Catholic is leading.",
        "Image 1 shows BRISTOL CENT. with 52 points.",
        "Image 2 shows BRISTOL CENT. with 52 points.",
        "Image 3 shows BRISTOL CENT. with 52 points.",
        "Image 1 shows E. CATHOLIC with 40 points.",
        "Image 2 shows E. CATHOLIC with 40 points.",
        "Image 3 shows E. CATHOLIC with 40 points."
      ],
      "linked_observations": [
        {
          "observation_id": "obs_01ed2f97a5060c50",
          "source_tool": "generic_purpose",
          "text": "Bristol Central is leading E. CATHOLIC at the end of the third quarter."
        },
        {
          "observation_id": "obs_2fa3db3b7833a3bc",
          "source_tool": "generic_purpose",
          "text": "The visible score at the end of the third quarter is 52 to 40."
        },
        {
          "observation_id": "obs_bad4029ef6a8bd94",
          "source_tool": "generic_purpose",
          "text": "Option A states Bristol Central is leading."
        },
        {
          "observation_id": "obs_362b81645bb7baf3",
          "source_tool": "generic_purpose",
          "text": "Option C states East Catholic is leading."
        },
        {
          "observation_id": "obs_ab5ab0ef63792e42",
          "source_tool": "generic_purpose",
          "text": "Option D states Bristol Central is leading."
        },
        {
          "observation_id": "obs_c6d29058f8df03e9",
          "source_tool": "generic_purpose",
          "text": "Option E states East Catholic is leading."
        },
        {
          "observation_id": "obs_2612aebdf4f80c91",
          "source_tool": "generic_purpose",
          "text": "Image 1 shows BRISTOL CENT. with 52 points."
        },
        {
          "observation_id": "obs_051cfd6551f07543",
          "source_tool": "generic_purpose",
          "text": "Image 2 shows BRISTOL CENT. with 52 points."
        }
      ]
    },
    {
      "artifact_id": "frame_116.00",
      "artifact_type": "frame",
      "relpath": "artifacts/0XB0BWhzNc/frames/frame_116.00.png",
      "time": {
        "timestamp_s": 116.0
      },
      "contains": [
        "In Image 3, BRISTOL CENT. has a score of 36.",
        "In Image 4, BRISTOL CENT. has a score of 52.",
        "In Image 5, BRISTOL CENT. has a score of 52.",
        "In Image 6, BRISTOL CENT. has a score of 52.",
        "The provided images do not show the end of the third quarter at 0:00.0.",
        "Option A states 55 to 40, Bristol Central leading.",
        "Option C states 55 to 40, East Catholic leading.",
        "Option D states 64 to 32, Bristol Central leading.",
        "Option E states 64 to 32, East Catholic leading.",
        "Image 3 scoreboard shows BRISTOL CENT.",
        "In Image 3, E. CATHOLIC has a score of 23.",
        "Image 4 scoreboard shows BRISTOL CENT."
      ],
      "linked_observations": [
        {
          "observation_id": "obs_8c906275ba0ee90c",
          "source_tool": "generic_purpose",
          "text": "In Image 3, BRISTOL CENT. has a score of 36."
        },
        {
          "observation_id": "obs_3dd3f5670ba329bb",
          "source_tool": "generic_purpose",
          "text": "In Image 4, BRISTOL CENT. has a score of 52."
        },
        {
          "observation_id": "obs_0a5f373ff19a051e",
          "source_tool": "generic_purpose",
          "text": "In Image 5, BRISTOL CENT. has a score of 52."
        },
        {
          "observation_id": "obs_90f4c287c4f0c8b0",
          "source_tool": "generic_purpose",
          "text": "In Image 6, BRISTOL CENT. has a score of 52."
        },
        {
          "observation_id": "obs_2bd3c544ff31c8c4",
          "source_tool": "generic_purpose",
          "text": "The provided images do not show the end of the third quarter at 0:00.0."
        },
        {
          "observation_id": "obs_f5dc8b4fa14e01d5",
          "source_tool": "generic_purpose",
          "text": "Option A states 55 to 40, Bristol Central leading."
        },
        {
          "observation_id": "obs_4e006f552343a599",
          "source_tool": "generic_purpose",
          "text": "Option C states 55 to 40, East Catholic leading."
        },
        {
          "observation_id": "obs_a55777f8bd0d96e0",
          "source_tool": "generic_purpose",
          "text": "Option D states 64 to 32, Bristol Central leading."
        }
      ],
      "linked_evidence": [
        {
          "evidence_id": "ev_02_a31973cc",
          "tool_name": "frame_retriever",
          "summary": "Retrieved 5 frame(s) across 3 input clip(s)."
        },
        {
          "evidence_id": "ev_02_665b2c44",
          "tool_name": "frame_retriever",
          "summary": "Retrieved 6 frame(s) across 3 input clip(s)."
        }
      ]
    },
    {
      "artifact_id": "frame_117.00",
      "artifact_type": "frame",
      "relpath": "artifacts/0XB0BWhzNc/frames/frame_117.00.png",
      "time": {
        "timestamp_s": 117.0
      },
      "contains": [
        "In Image 3, BRISTOL CENT. has a score of 36.",
        "In Image 4, BRISTOL CENT. has a score of 52.",
        "In Image 5, BRISTOL CENT. has a score of 52.",
        "In Image 6, BRISTOL CENT. has a score of 52.",
        "The provided images do not show the end of the third quarter at 0:00.0.",
        "Option A states 55 to 40, Bristol Central leading.",
        "Option C states 55 to 40, East Catholic leading.",
        "Option D states 64 to 32, Bristol Central leading.",
        "Option E states 64 to 32, East Catholic leading.",
        "Image 3 scoreboard shows BRISTOL CENT.",
        "In Image 3, E. CATHOLIC has a score of 23.",
        "Image 4 scoreboard shows BRISTOL CENT."
      ],
      "linked_observations": [
        {
          "observation_id": "obs_8c906275ba0ee90c",
          "source_tool": "generic_purpose",
          "text": "In Image 3, BRISTOL CENT. has a score of 36."
        },
        {
          "observation_id": "obs_3dd3f5670ba329bb",
          "source_tool": "generic_purpose",
          "text": "In Image 4, BRISTOL CENT. has a score of 52."
        },
        {
          "observation_id": "obs_0a5f373ff19a051e",
          "source_tool": "generic_purpose",
          "text": "In Image 5, BRISTOL CENT. has a score of 52."
        },
        {
          "observation_id": "obs_90f4c287c4f0c8b0",
          "source_tool": "generic_purpose",
          "text": "In Image 6, BRISTOL CENT. has a score of 52."
        },
        {
          "observation_id": "obs_2bd3c544ff31c8c4",
          "source_tool": "generic_purpose",
          "text": "The provided images do not show the end of the third quarter at 0:00.0."
        },
        {
          "observation_id": "obs_f5dc8b4fa14e01d5",
          "source_tool": "generic_purpose",
          "text": "Option A states 55 to 40, Bristol Central leading."
        },
        {
          "observation_id": "obs_4e006f552343a599",
          "source_tool": "generic_purpose",
          "text": "Option C states 55 to 40, East Catholic leading."
        },
        {
          "observation_id": "obs_a55777f8bd0d96e0",
          "source_tool": "generic_purpose",
          "text": "Option D states 64 to 32, Bristol Central leading."
        }
      ],
      "linked_evidence": [
        {
          "evidence_id": "ev_02_a31973cc",
          "tool_name": "frame_retriever",
          "summary": "Retrieved 5 frame(s) across 3 input clip(s)."
        },
        {
          "evidence_id": "ev_02_665b2c44",
          "tool_name": "frame_retriever",
          "summary": "Retrieved 6 frame(s) across 3 input clip(s)."
        }
      ]
    },
    {
      "artifact_id": "frame_118.00",
      "artifact_type": "frame",
      "relpath": "artifacts/0XB0BWhzNc/frames/frame_118.00.png",
      "time": {
        "timestamp_s": 118.0
      },
      "contains": [
        "In Image 3, BRISTOL CENT. has a score of 36.",
        "In Image 4, BRISTOL CENT. has a score of 52.",
        "In Image 5, BRISTOL CENT. has a score of 52.",
        "In Image 6, BRISTOL CENT. has a score of 52.",
        "The provided images do not show the end of the third quarter at 0:00.0.",
        "Option A states 55 to 40, Bristol Central leading.",
        "Option C states 55 to 40, East Catholic leading.",
        "Option D states 64 to 32, Bristol Central leading.",
        "Option E states 64 to 32, East Catholic leading.",
        "Image 3 scoreboard shows BRISTOL CENT.",
        "In Image 3, E. CATHOLIC has a score of 23.",
        "Image 4 scoreboard shows BRISTOL CENT."
      ],
      "linked_observations": [
        {
          "observation_id": "obs_8c906275ba0ee90c",
          "source_tool": "generic_purpose",
          "text": "In Image 3, BRISTOL CENT. has a score of 36."
        },
        {
          "observation_id": "obs_3dd3f5670ba329bb",
          "source_tool": "generic_purpose",
          "text": "In Image 4, BRISTOL CENT. has a score of 52."
        },
        {
          "observation_id": "obs_0a5f373ff19a051e",
          "source_tool": "generic_purpose",
          "text": "In Image 5, BRISTOL CENT. has a score of 52."
        },
        {
          "observation_id": "obs_90f4c287c4f0c8b0",
          "source_tool": "generic_purpose",
          "text": "In Image 6, BRISTOL CENT. has a score of 52."
        },
        {
          "observation_id": "obs_2bd3c544ff31c8c4",
          "source_tool": "generic_purpose",
          "text": "The provided images do not show the end of the third quarter at 0:00.0."
        },
        {
          "observation_id": "obs_f5dc8b4fa14e01d5",
          "source_tool": "generic_purpose",
          "text": "Option A states 55 to 40, Bristol Central leading."
        },
        {
          "observation_id": "obs_4e006f552343a599",
          "source_tool": "generic_purpose",
          "text": "Option C states 55 to 40, East Catholic leading."
        },
        {
          "observation_id": "obs_a55777f8bd0d96e0",
          "source_tool": "generic_purpose",
          "text": "Option D states 64 to 32, Bristol Central leading."
        }
      ],
      "linked_evidence": [
        {
          "evidence_id": "ev_02_a31973cc",
          "tool_name": "frame_retriever",
          "summary": "Retrieved 5 frame(s) across 3 input clip(s)."
        },
        {
          "evidence_id": "ev_02_665b2c44",
          "tool_name": "frame_retriever",
          "summary": "Retrieved 6 frame(s) across 3 input clip(s)."
        }
      ]
    },
    {
      "artifact_id": "frame_124.00",
      "artifact_type": "frame",
      "relpath": "artifacts/0XB0BWhzNc/frames/frame_124.00.png",
      "time": {
        "timestamp_s": 124.0
      },
      "contains": [
        "Bristol Central is leading E. CATHOLIC at the end of the third quarter.",
        "The visible score at the end of the third quarter is 52 to 40.",
        "Option A states Bristol Central is leading.",
        "Option C states East Catholic is leading.",
        "Option D states Bristol Central is leading.",
        "Option E states East Catholic is leading.",
        "Image 1 shows BRISTOL CENT. with 52 points.",
        "Image 2 shows BRISTOL CENT. with 52 points.",
        "Image 3 shows BRISTOL CENT. with 52 points.",
        "Image 1 shows E. CATHOLIC with 40 points.",
        "Image 2 shows E. CATHOLIC with 40 points.",
        "Image 3 shows E. CATHOLIC with 40 points."
      ],
      "linked_observations": [
        {
          "observation_id": "obs_01ed2f97a5060c50",
          "source_tool": "generic_purpose",
          "text": "Bristol Central is leading E. CATHOLIC at the end of the third quarter."
        },
        {
          "observation_id": "obs_2fa3db3b7833a3bc",
          "source_tool": "generic_purpose",
          "text": "The visible score at the end of the third quarter is 52 to 40."
        },
        {
          "observation_id": "obs_bad4029ef6a8bd94",
          "source_tool": "generic_purpose",
          "text": "Option A states Bristol Central is leading."
        },
        {
          "observation_id": "obs_362b81645bb7baf3",
          "source_tool": "generic_purpose",
          "text": "Option C states East Catholic is leading."
        },
        {
          "observation_id": "obs_ab5ab0ef63792e42",
          "source_tool": "generic_purpose",
          "text": "Option D states Bristol Central is leading."
        },
        {
          "observation_id": "obs_c6d29058f8df03e9",
          "source_tool": "generic_purpose",
          "text": "Option E states East Catholic is leading."
        },
        {
          "observation_id": "obs_2612aebdf4f80c91",
          "source_tool": "generic_purpose",
          "text": "Image 1 shows BRISTOL CENT. with 52 points."
        },
        {
          "observation_id": "obs_051cfd6551f07543",
          "source_tool": "generic_purpose",
          "text": "Image 2 shows BRISTOL CENT. with 52 points."
        }
      ],
      "linked_evidence": [
        {
          "evidence_id": "ev_01_cddd1e02",
          "tool_name": "frame_retriever",
          "summary": "Retrieved 3 frame(s) across 1 input clip(s)."
        },
        {
          "evidence_id": "ev_02_a31973cc",
          "tool_name": "frame_retriever",
          "summary": "Retrieved 5 frame(s) across 3 input clip(s)."
        },
        {
          "evidence_id": "ev_02_665b2c44",
          "tool_name": "frame_retriever",
          "summary": "Retrieved 6 frame(s) across 3 input clip(s)."
        }
      ]
    },
    {
      "artifact_id": "frame_125.00",
      "artifact_type": "frame",
      "relpath": "artifacts/0XB0BWhzNc/frames/frame_125.00.png",
      "time": {
        "timestamp_s": 125.0
      },
      "contains": [
        "Bristol Central is leading E. CATHOLIC at the end of the third quarter.",
        "Bristol Central leads East Catholic.",
        "The visible score at the end of the third quarter is 52 to 40.",
        "The score at the end of the third quarter is 52 to 40.",
        "Option A states Bristol Central is leading.",
        "Option C states East Catholic is leading.",
        "Option D states Bristol Central is leading.",
        "Option E states East Catholic is leading.",
        "Option A states \"55 to 40, Bristol Central leading\".",
        "Option C states \"55 to 40, East Catholic leading\".",
        "Option D states \"64 to 32, Bristol Central leading\".",
        "Option E states \"64 to 32, East Catholic leading\"."
      ],
      "linked_observations": [
        {
          "observation_id": "obs_01ed2f97a5060c50",
          "source_tool": "generic_purpose",
          "text": "Bristol Central is leading E. CATHOLIC at the end of the third quarter."
        },
        {
          "observation_id": "obs_d0bc303695c5b976",
          "source_tool": "generic_purpose",
          "text": "Bristol Central leads East Catholic."
        },
        {
          "observation_id": "obs_2fa3db3b7833a3bc",
          "source_tool": "generic_purpose",
          "text": "The visible score at the end of the third quarter is 52 to 40."
        },
        {
          "observation_id": "obs_86ec28991d73642c",
          "source_tool": "generic_purpose",
          "text": "The score at the end of the third quarter is 52 to 40."
        },
        {
          "observation_id": "obs_bad4029ef6a8bd94",
          "source_tool": "generic_purpose",
          "text": "Option A states Bristol Central is leading."
        },
        {
          "observation_id": "obs_362b81645bb7baf3",
          "source_tool": "generic_purpose",
          "text": "Option C states East Catholic is leading."
        },
        {
          "observation_id": "obs_ab5ab0ef63792e42",
          "source_tool": "generic_purpose",
          "text": "Option D states Bristol Central is leading."
        },
        {
          "observation_id": "obs_c6d29058f8df03e9",
          "source_tool": "generic_purpose",
          "text": "Option E states East Catholic is leading."
        }
      ],
      "linked_evidence": [
        {
          "evidence_id": "ev_01_cddd1e02",
          "tool_name": "frame_retriever",
          "summary": "Retrieved 3 frame(s) across 1 input clip(s)."
        },
        {
          "evidence_id": "ev_02_a31973cc",
          "tool_name": "frame_retriever",
          "summary": "Retrieved 5 frame(s) across 3 input clip(s)."
        },
        {
          "evidence_id": "ev_02_665b2c44",
          "tool_name": "frame_retriever",
          "summary": "Retrieved 6 frame(s) across 3 input clip(s)."
        }
      ]
    },
    {
      "artifact_id": "frame_126.00",
      "artifact_type": "frame",
      "relpath": "artifacts/0XB0BWhzNc/frames/frame_126.00.png",
      "time": {
        "timestamp_s": 126.0
      },
      "contains": [
        "Bristol Central is leading E. CATHOLIC at the end of the third quarter.",
        "Bristol Central leads East Catholic.",
        "The visible score at the end of the third quarter is 52 to 40.",
        "The score at the end of the third quarter is 52 to 40.",
        "Option A states Bristol Central is leading.",
        "Option C states East Catholic is leading.",
        "Option D states Bristol Central is leading.",
        "Option E states East Catholic is leading.",
        "Option A states \"55 to 40, Bristol Central leading\".",
        "Option C states \"55 to 40, East Catholic leading\".",
        "Option D states \"64 to 32, Bristol Central leading\".",
        "Option E states \"64 to 32, East Catholic leading\"."
      ],
      "linked_observations": [
        {
          "observation_id": "obs_01ed2f97a5060c50",
          "source_tool": "generic_purpose",
          "text": "Bristol Central is leading E. CATHOLIC at the end of the third quarter."
        },
        {
          "observation_id": "obs_eda4228cc0acdfaf",
          "source_tool": "generic_purpose",
          "text": "At the end of the 3rd quarter, the score is Bristol Cent. 52 and E. Catholic 40."
        },
        {
          "observation_id": "obs_d0bc303695c5b976",
          "source_tool": "generic_purpose",
          "text": "Bristol Central leads East Catholic."
        },
        {
          "observation_id": "obs_2fa3db3b7833a3bc",
          "source_tool": "generic_purpose",
          "text": "The visible score at the end of the third quarter is 52 to 40."
        },
        {
          "observation_id": "obs_86ec28991d73642c",
          "source_tool": "generic_purpose",
          "text": "The score at the end of the third quarter is 52 to 40."
        },
        {
          "observation_id": "obs_bad4029ef6a8bd94",
          "source_tool": "generic_purpose",
          "text": "Option A states Bristol Central is leading."
        },
        {
          "observation_id": "obs_362b81645bb7baf3",
          "source_tool": "generic_purpose",
          "text": "Option C states East Catholic is leading."
        },
        {
          "observation_id": "obs_ab5ab0ef63792e42",
          "source_tool": "generic_purpose",
          "text": "Option D states Bristol Central is leading."
        }
      ],
      "linked_evidence": [
        {
          "evidence_id": "ev_01_cddd1e02",
          "tool_name": "frame_retriever",
          "summary": "Retrieved 3 frame(s) across 1 input clip(s)."
        },
        {
          "evidence_id": "ev_02_a31973cc",
          "tool_name": "frame_retriever",
          "summary": "Retrieved 5 frame(s) across 3 input clip(s)."
        }
      ]
    },
    {
      "artifact_id": "frame_58.00",
      "artifact_type": "frame",
      "relpath": "artifacts/0XB0BWhzNc/frames/frame_58.00.png",
      "time": {
        "timestamp_s": 58.0
      },
      "contains": [
        "In Image 3, BRISTOL CENT. has a score of 36.",
        "In Image 4, BRISTOL CENT. has a score of 52.",
        "In Image 5, BRISTOL CENT. has a score of 52.",
        "In Image 6, BRISTOL CENT. has a score of 52.",
        "The provided images do not show the end of the third quarter at 0:00.0.",
        "Option A states 55 to 40, Bristol Central leading.",
        "Option C states 55 to 40, East Catholic leading.",
        "Option D states 64 to 32, Bristol Central leading.",
        "Option E states 64 to 32, East Catholic leading.",
        "Image 3 scoreboard shows BRISTOL CENT.",
        "In Image 3, E. CATHOLIC has a score of 23.",
        "Image 4 scoreboard shows BRISTOL CENT."
      ],
      "linked_observations": [
        {
          "observation_id": "obs_8c906275ba0ee90c",
          "source_tool": "generic_purpose",
          "text": "In Image 3, BRISTOL CENT. has a score of 36."
        },
        {
          "observation_id": "obs_3dd3f5670ba329bb",
          "source_tool": "generic_purpose",
          "text": "In Image 4, BRISTOL CENT. has a score of 52."
        },
        {
          "observation_id": "obs_0a5f373ff19a051e",
          "source_tool": "generic_purpose",
          "text": "In Image 5, BRISTOL CENT. has a score of 52."
        },
        {
          "observation_id": "obs_90f4c287c4f0c8b0",
          "source_tool": "generic_purpose",
          "text": "In Image 6, BRISTOL CENT. has a score of 52."
        },
        {
          "observation_id": "obs_2bd3c544ff31c8c4",
          "source_tool": "generic_purpose",
          "text": "The provided images do not show the end of the third quarter at 0:00.0."
        },
        {
          "observation_id": "obs_f5dc8b4fa14e01d5",
          "source_tool": "generic_purpose",
          "text": "Option A states 55 to 40, Bristol Central leading."
        },
        {
          "observation_id": "obs_4e006f552343a599",
          "source_tool": "generic_purpose",
          "text": "Option C states 55 to 40, East Catholic leading."
        },
        {
          "observation_id": "obs_a55777f8bd0d96e0",
          "source_tool": "generic_purpose",
          "text": "Option D states 64 to 32, Bristol Central leading."
        }
      ],
      "linked_evidence": [
        {
          "evidence_id": "ev_02_665b2c44",
          "tool_name": "frame_retriever",
          "summary": "Retrieved 6 frame(s) across 3 input clip(s)."
        }
      ]
    },
    {
      "artifact_id": "frame_59.00",
      "artifact_type": "frame",
      "relpath": "artifacts/0XB0BWhzNc/frames/frame_59.00.png",
      "time": {
        "timestamp_s": 59.0
      },
      "contains": [
        "In Image 3, BRISTOL CENT. has a score of 36.",
        "In Image 4, BRISTOL CENT. has a score of 52.",
        "In Image 5, BRISTOL CENT. has a score of 52.",
        "In Image 6, BRISTOL CENT. has a score of 52.",
        "The provided images do not show the end of the third quarter at 0:00.0.",
        "Option A states 55 to 40, Bristol Central leading.",
        "Option C states 55 to 40, East Catholic leading.",
        "Option D states 64 to 32, Bristol Central leading.",
        "Option E states 64 to 32, East Catholic leading.",
        "Image 3 scoreboard shows BRISTOL CENT.",
        "In Image 3, E. CATHOLIC has a score of 23.",
        "Image 4 scoreboard shows BRISTOL CENT."
      ],
      "linked_observations": [
        {
          "observation_id": "obs_8c906275ba0ee90c",
          "source_tool": "generic_purpose",
          "text": "In Image 3, BRISTOL CENT. has a score of 36."
        },
        {
          "observation_id": "obs_3dd3f5670ba329bb",
          "source_tool": "generic_purpose",
          "text": "In Image 4, BRISTOL CENT. has a score of 52."
        },
        {
          "observation_id": "obs_0a5f373ff19a051e",
          "source_tool": "generic_purpose",
          "text": "In Image 5, BRISTOL CENT. has a score of 52."
        },
        {
          "observation_id": "obs_90f4c287c4f0c8b0",
          "source_tool": "generic_purpose",
          "text": "In Image 6, BRISTOL CENT. has a score of 52."
        },
        {
          "observation_id": "obs_2bd3c544ff31c8c4",
          "source_tool": "generic_purpose",
          "text": "The provided images do not show the end of the third quarter at 0:00.0."
        },
        {
          "observation_id": "obs_f5dc8b4fa14e01d5",
          "source_tool": "generic_purpose",
          "text": "Option A states 55 to 40, Bristol Central leading."
        },
        {
          "observation_id": "obs_4e006f552343a599",
          "source_tool": "generic_purpose",
          "text": "Option C states 55 to 40, East Catholic leading."
        },
        {
          "observation_id": "obs_a55777f8bd0d96e0",
          "source_tool": "generic_purpose",
          "text": "Option D states 64 to 32, Bristol Central leading."
        }
      ],
      "linked_evidence": [
        {
          "evidence_id": "ev_02_665b2c44",
          "tool_name": "frame_retriever",
          "summary": "Retrieved 6 frame(s) across 3 input clip(s)."
        }
      ]
    },
    {
      "artifact_id": "frame_60.00",
      "artifact_type": "frame",
      "relpath": "artifacts/0XB0BWhzNc/frames/frame_60.00.png",
      "time": {
        "timestamp_s": 60.0
      },
      "contains": [
        "In Image 3, BRISTOL CENT. has a score of 36.",
        "In Image 4, BRISTOL CENT. has a score of 52.",
        "In Image 5, BRISTOL CENT. has a score of 52.",
        "In Image 6, BRISTOL CENT. has a score of 52.",
        "The provided images do not show the end of the third quarter at 0:00.0.",
        "Option A states 55 to 40, Bristol Central leading.",
        "Option C states 55 to 40, East Catholic leading.",
        "Option D states 64 to 32, Bristol Central leading.",
        "Option E states 64 to 32, East Catholic leading.",
        "Image 3 scoreboard shows BRISTOL CENT.",
        "In Image 3, E. CATHOLIC has a score of 23.",
        "Image 4 scoreboard shows BRISTOL CENT."
      ],
      "linked_observations": [
        {
          "observation_id": "obs_8c906275ba0ee90c",
          "source_tool": "generic_purpose",
          "text": "In Image 3, BRISTOL CENT. has a score of 36."
        },
        {
          "observation_id": "obs_3dd3f5670ba329bb",
          "source_tool": "generic_purpose",
          "text": "In Image 4, BRISTOL CENT. has a score of 52."
        },
        {
          "observation_id": "obs_0a5f373ff19a051e",
          "source_tool": "generic_purpose",
          "text": "In Image 5, BRISTOL CENT. has a score of 52."
        },
        {
          "observation_id": "obs_90f4c287c4f0c8b0",
          "source_tool": "generic_purpose",
          "text": "In Image 6, BRISTOL CENT. has a score of 52."
        },
        {
          "observation_id": "obs_2bd3c544ff31c8c4",
          "source_tool": "generic_purpose",
          "text": "The provided images do not show the end of the third quarter at 0:00.0."
        },
        {
          "observation_id": "obs_f5dc8b4fa14e01d5",
          "source_tool": "generic_purpose",
          "text": "Option A states 55 to 40, Bristol Central leading."
        },
        {
          "observation_id": "obs_4e006f552343a599",
          "source_tool": "generic_purpose",
          "text": "Option C states 55 to 40, East Catholic leading."
        },
        {
          "observation_id": "obs_a55777f8bd0d96e0",
          "source_tool": "generic_purpose",
          "text": "Option D states 64 to 32, Bristol Central leading."
        }
      ],
      "linked_evidence": [
        {
          "evidence_id": "ev_02_665b2c44",
          "tool_name": "frame_retriever",
          "summary": "Retrieved 6 frame(s) across 3 input clip(s)."
        }
      ]
    },
    {
      "artifact_id": "frame_0.00",
      "artifact_type": "frame",
      "relpath": "artifacts/0XB0BWhzNc/frames/frame_0.00.png",
      "time": {
        "timestamp_s": 0.0
      },
      "contains": [
        "The score at the end of the third quarter is indeterminate based only on the supplied evidence.",
        "The provided images contain no visual evidence of the third quarter score.",
        "Image 1 shows BRISTOL CENT. 2.",
        "Image 2 shows BRISTOL CENT. 2.",
        "Image 3 shows BRISTOL CENT. 2.",
        "Image 4 shows BRISTOL CENT. 2.",
        "Image 5 shows BRISTOL CENT. 5.",
        "Image 1 shows E. CATHOLIC 3.",
        "Image 2 shows E. CATHOLIC 3.",
        "Image 3 shows E. CATHOLIC 3.",
        "Image 4 shows E. CATHOLIC 3.",
        "Image 5 shows E. CATHOLIC 3."
      ],
      "linked_observations": [
        {
          "observation_id": "obs_efc56cce383f14c6",
          "source_tool": "generic_purpose",
          "text": "The score at the end of the third quarter is indeterminate based only on the supplied evidence."
        },
        {
          "observation_id": "obs_1b41704402eadd6f",
          "source_tool": "generic_purpose",
          "text": "The provided images contain no visual evidence of the third quarter score."
        },
        {
          "observation_id": "obs_af91db9b15af9405",
          "source_tool": "generic_purpose",
          "text": "Image 1 shows BRISTOL CENT. 2."
        },
        {
          "observation_id": "obs_55a00d2fa9b0a352",
          "source_tool": "generic_purpose",
          "text": "Image 2 shows BRISTOL CENT. 2."
        },
        {
          "observation_id": "obs_c1098e0a5a976711",
          "source_tool": "generic_purpose",
          "text": "Image 3 shows BRISTOL CENT. 2."
        },
        {
          "observation_id": "obs_72ea575f5f18d21c",
          "source_tool": "generic_purpose",
          "text": "Image 4 shows BRISTOL CENT. 2."
        },
        {
          "observation_id": "obs_ae516f782629086d",
          "source_tool": "generic_purpose",
          "text": "Image 5 shows BRISTOL CENT. 5."
        },
        {
          "observation_id": "obs_c27cffe9cb5af786",
          "source_tool": "generic_purpose",
          "text": "Image 1 shows E. CATHOLIC 3."
        }
      ],
      "linked_evidence": [
        {
          "evidence_id": "ev_02_a31973cc",
          "tool_name": "frame_retriever",
          "summary": "Retrieved 5 frame(s) across 3 input clip(s)."
        }
      ]
    },
    {
      "artifact_id": "frame_1.00",
      "artifact_type": "frame",
      "relpath": "artifacts/0XB0BWhzNc/frames/frame_1.00.png",
      "time": {
        "timestamp_s": 1.0
      },
      "contains": [
        "The score at the end of the third quarter is indeterminate based only on the supplied evidence.",
        "The provided images contain no visual evidence of the third quarter score.",
        "Image 1 shows BRISTOL CENT. 2.",
        "Image 2 shows BRISTOL CENT. 2.",
        "Image 3 shows BRISTOL CENT. 2.",
        "Image 4 shows BRISTOL CENT. 2.",
        "Image 5 shows BRISTOL CENT. 5.",
        "Image 1 shows E. CATHOLIC 3.",
        "Image 2 shows E. CATHOLIC 3.",
        "Image 3 shows E. CATHOLIC 3.",
        "Image 4 shows E. CATHOLIC 3.",
        "Image 5 shows E. CATHOLIC 3."
      ],
      "linked_observations": [
        {
          "observation_id": "obs_efc56cce383f14c6",
          "source_tool": "generic_purpose",
          "text": "The score at the end of the third quarter is indeterminate based only on the supplied evidence."
        },
        {
          "observation_id": "obs_1b41704402eadd6f",
          "source_tool": "generic_purpose",
          "text": "The provided images contain no visual evidence of the third quarter score."
        },
        {
          "observation_id": "obs_af91db9b15af9405",
          "source_tool": "generic_purpose",
          "text": "Image 1 shows BRISTOL CENT. 2."
        },
        {
          "observation_id": "obs_55a00d2fa9b0a352",
          "source_tool": "generic_purpose",
          "text": "Image 2 shows BRISTOL CENT. 2."
        },
        {
          "observation_id": "obs_c1098e0a5a976711",
          "source_tool": "generic_purpose",
          "text": "Image 3 shows BRISTOL CENT. 2."
        },
        {
          "observation_id": "obs_72ea575f5f18d21c",
          "source_tool": "generic_purpose",
          "text": "Image 4 shows BRISTOL CENT. 2."
        },
        {
          "observation_id": "obs_ae516f782629086d",
          "source_tool": "generic_purpose",
          "text": "Image 5 shows BRISTOL CENT. 5."
        },
        {
          "observation_id": "obs_c27cffe9cb5af786",
          "source_tool": "generic_purpose",
          "text": "Image 1 shows E. CATHOLIC 3."
        }
      ],
      "linked_evidence": [
        {
          "evidence_id": "ev_02_a31973cc",
          "tool_name": "frame_retriever",
          "summary": "Retrieved 5 frame(s) across 3 input clip(s)."
        }
      ]
    },
    {
      "artifact_id": "frame_3.00",
      "artifact_type": "frame",
      "relpath": "artifacts/0XB0BWhzNc/frames/frame_3.00.png",
      "time": {
        "timestamp_s": 3.0
      },
      "contains": [
        "The score at the end of the third quarter is indeterminate based only on the supplied evidence.",
        "The provided images contain no visual evidence of the third quarter score.",
        "Image 1 shows BRISTOL CENT. 2.",
        "Image 2 shows BRISTOL CENT. 2.",
        "Image 3 shows BRISTOL CENT. 2.",
        "Image 4 shows BRISTOL CENT. 2.",
        "Image 5 shows BRISTOL CENT. 5.",
        "Image 1 shows E. CATHOLIC 3.",
        "Image 2 shows E. CATHOLIC 3.",
        "Image 3 shows E. CATHOLIC 3.",
        "Image 4 shows E. CATHOLIC 3.",
        "Image 5 shows E. CATHOLIC 3."
      ],
      "linked_observations": [
        {
          "observation_id": "obs_efc56cce383f14c6",
          "source_tool": "generic_purpose",
          "text": "The score at the end of the third quarter is indeterminate based only on the supplied evidence."
        },
        {
          "observation_id": "obs_1b41704402eadd6f",
          "source_tool": "generic_purpose",
          "text": "The provided images contain no visual evidence of the third quarter score."
        },
        {
          "observation_id": "obs_af91db9b15af9405",
          "source_tool": "generic_purpose",
          "text": "Image 1 shows BRISTOL CENT. 2."
        },
        {
          "observation_id": "obs_55a00d2fa9b0a352",
          "source_tool": "generic_purpose",
          "text": "Image 2 shows BRISTOL CENT. 2."
        },
        {
          "observation_id": "obs_c1098e0a5a976711",
          "source_tool": "generic_purpose",
          "text": "Image 3 shows BRISTOL CENT. 2."
        },
        {
          "observation_id": "obs_72ea575f5f18d21c",
          "source_tool": "generic_purpose",
          "text": "Image 4 shows BRISTOL CENT. 2."
        },
        {
          "observation_id": "obs_ae516f782629086d",
          "source_tool": "generic_purpose",
          "text": "Image 5 shows BRISTOL CENT. 5."
        },
        {
          "observation_id": "obs_c27cffe9cb5af786",
          "source_tool": "generic_purpose",
          "text": "Image 1 shows E. CATHOLIC 3."
        }
      ],
      "linked_evidence": [
        {
          "evidence_id": "ev_02_a31973cc",
          "tool_name": "frame_retriever",
          "summary": "Retrieved 5 frame(s) across 3 input clip(s)."
        }
      ]
    },
    {
      "artifact_id": "frame_4.00",
      "artifact_type": "frame",
      "relpath": "artifacts/0XB0BWhzNc/frames/frame_4.00.png",
      "time": {
        "timestamp_s": 4.0
      },
      "contains": [
        "The score at the end of the third quarter is indeterminate based only on the supplied evidence.",
        "The provided images contain no visual evidence of the third quarter score.",
        "Image 1 shows BRISTOL CENT. 2.",
        "Image 2 shows BRISTOL CENT. 2.",
        "Image 3 shows BRISTOL CENT. 2.",
        "Image 4 shows BRISTOL CENT. 2.",
        "Image 5 shows BRISTOL CENT. 5.",
        "Image 1 shows E. CATHOLIC 3.",
        "Image 2 shows E. CATHOLIC 3.",
        "Image 3 shows E. CATHOLIC 3.",
        "Image 4 shows E. CATHOLIC 3.",
        "Image 5 shows E. CATHOLIC 3."
      ],
      "linked_observations": [
        {
          "observation_id": "obs_efc56cce383f14c6",
          "source_tool": "generic_purpose",
          "text": "The score at the end of the third quarter is indeterminate based only on the supplied evidence."
        },
        {
          "observation_id": "obs_1b41704402eadd6f",
          "source_tool": "generic_purpose",
          "text": "The provided images contain no visual evidence of the third quarter score."
        },
        {
          "observation_id": "obs_af91db9b15af9405",
          "source_tool": "generic_purpose",
          "text": "Image 1 shows BRISTOL CENT. 2."
        },
        {
          "observation_id": "obs_55a00d2fa9b0a352",
          "source_tool": "generic_purpose",
          "text": "Image 2 shows BRISTOL CENT. 2."
        },
        {
          "observation_id": "obs_c1098e0a5a976711",
          "source_tool": "generic_purpose",
          "text": "Image 3 shows BRISTOL CENT. 2."
        },
        {
          "observation_id": "obs_72ea575f5f18d21c",
          "source_tool": "generic_purpose",
          "text": "Image 4 shows BRISTOL CENT. 2."
        },
        {
          "observation_id": "obs_ae516f782629086d",
          "source_tool": "generic_purpose",
          "text": "Image 5 shows BRISTOL CENT. 5."
        },
        {
          "observation_id": "obs_c27cffe9cb5af786",
          "source_tool": "generic_purpose",
          "text": "Image 1 shows E. CATHOLIC 3."
        }
      ],
      "linked_evidence": [
        {
          "evidence_id": "ev_02_a31973cc",
          "tool_name": "frame_retriever",
          "summary": "Retrieved 5 frame(s) across 3 input clip(s)."
        }
      ]
    },
    {
      "artifact_id": "frame_5.00",
      "artifact_type": "frame",
      "relpath": "artifacts/0XB0BWhzNc/frames/frame_5.00.png",
      "time": {
        "timestamp_s": 5.0
      },
      "contains": [
        "The score at the end of the third quarter is indeterminate based only on the supplied evidence.",
        "The provided images contain no visual evidence of the third quarter score.",
        "Image 1 shows BRISTOL CENT. 2.",
        "Image 2 shows BRISTOL CENT. 2.",
        "Image 3 shows BRISTOL CENT. 2.",
        "Image 4 shows BRISTOL CENT. 2.",
        "Image 5 shows BRISTOL CENT. 5.",
        "Image 1 shows E. CATHOLIC 3.",
        "Image 2 shows E. CATHOLIC 3.",
        "Image 3 shows E. CATHOLIC 3.",
        "Image 4 shows E. CATHOLIC 3.",
        "Image 5 shows E. CATHOLIC 3."
      ],
      "linked_observations": [
        {
          "observation_id": "obs_efc56cce383f14c6",
          "source_tool": "generic_purpose",
          "text": "The score at the end of the third quarter is indeterminate based only on the supplied evidence."
        },
        {
          "observation_id": "obs_1b41704402eadd6f",
          "source_tool": "generic_purpose",
          "text": "The provided images contain no visual evidence of the third quarter score."
        },
        {
          "observation_id": "obs_af91db9b15af9405",
          "source_tool": "generic_purpose",
          "text": "Image 1 shows BRISTOL CENT. 2."
        },
        {
          "observation_id": "obs_55a00d2fa9b0a352",
          "source_tool": "generic_purpose",
          "text": "Image 2 shows BRISTOL CENT. 2."
        },
        {
          "observation_id": "obs_c1098e0a5a976711",
          "source_tool": "generic_purpose",
          "text": "Image 3 shows BRISTOL CENT. 2."
        },
        {
          "observation_id": "obs_72ea575f5f18d21c",
          "source_tool": "generic_purpose",
          "text": "Image 4 shows BRISTOL CENT. 2."
        },
        {
          "observation_id": "obs_ae516f782629086d",
          "source_tool": "generic_purpose",
          "text": "Image 5 shows BRISTOL CENT. 5."
        },
        {
          "observation_id": "obs_c27cffe9cb5af786",
          "source_tool": "generic_purpose",
          "text": "Image 1 shows E. CATHOLIC 3."
        }
      ],
      "linked_evidence": [
        {
          "evidence_id": "ev_02_a31973cc",
          "tool_name": "frame_retriever",
          "summary": "Retrieved 5 frame(s) across 3 input clip(s)."
        }
      ]
    }
  ]
}
