[
  {
    "observation_id": "obs_1f98d42030ff46bf",
    "subject": "woman in gray shirt volunteering at Inner City Tennis on an indoor tennis court, demonstrating or teaching a drill with side steps and ball tosses",
    "subject_type": "event_query",
    "predicate": "present_in_interval",
    "object_text": "117.00s-119.00s",
    "object_type": "time_interval",
    "numeric_value": null,
    "unit": null,
    "time_start_s": 117.0,
    "time_end_s": 119.0,
    "frame_ts_s": null,
    "bbox": null,
    "speaker_id": null,
    "confidence": 1.0,
    "source_tool": "visual_temporal_grounder",
    "source_artifact_refs": [],
    "direct_or_derived": "direct",
    "atomic_text": "\"woman in gray shirt volunteering at Inner City Tennis on an indoor tennis court, demonstrating or teaching a drill with side steps and ball tosses\" is present from 117.00s to 119.00s.",
    "metadata": {
      "observation_id": "obs_1f98d42030ff46bf"
    }
  },
  {
    "observation_id": "obs_0de66ffa8dfd6ef5",
    "subject": "woman in gray shirt volunteering at Inner City Tennis on an indoor tennis court, demonstrating or teaching a drill with side steps and ball tosses",
    "subject_type": "event_query",
    "predicate": "present_in_interval",
    "object_text": "120.00s-128.00s",
    "object_type": "time_interval",
    "numeric_value": null,
    "unit": null,
    "time_start_s": 120.0,
    "time_end_s": 128.0,
    "frame_ts_s": null,
    "bbox": null,
    "speaker_id": null,
    "confidence": 1.0,
    "source_tool": "visual_temporal_grounder",
    "source_artifact_refs": [],
    "direct_or_derived": "direct",
    "atomic_text": "\"woman in gray shirt volunteering at Inner City Tennis on an indoor tennis court, demonstrating or teaching a drill with side steps and ball tosses\" is present from 120.00s to 128.00s.",
    "metadata": {
      "observation_id": "obs_0de66ffa8dfd6ef5"
    }
  }
]
