[
  {
    "artifact_id": "frame_176.00",
    "kind": "frame",
    "relpath": "artifacts/91ub3om9Fg0/frames/frame_176.00.png",
    "media_type": "image",
    "source_tool": "frame_retriever",
    "metadata": {
      "source_name": "frame_176.00.png",
      "copied": true,
      "media_type": "image",
      "size_bytes": 150138
    }
  },
  {
    "artifact_id": "frame_177.00",
    "kind": "frame",
    "relpath": "artifacts/91ub3om9Fg0/frames/frame_177.00.png",
    "media_type": "image",
    "source_tool": "frame_retriever",
    "metadata": {
      "source_name": "frame_177.00.png",
      "copied": true,
      "media_type": "image",
      "size_bytes": 147097
    }
  },
  {
    "artifact_id": "frame_178.00",
    "kind": "frame",
    "relpath": "artifacts/91ub3om9Fg0/frames/frame_178.00.png",
    "media_type": "image",
    "source_tool": "frame_retriever",
    "metadata": {
      "source_name": "frame_178.00.png",
      "copied": true,
      "media_type": "image",
      "size_bytes": 194753
    }
  },
  {
    "artifact_id": "frame_179.00",
    "kind": "frame",
    "relpath": "artifacts/91ub3om9Fg0/frames/frame_179.00.png",
    "media_type": "image",
    "source_tool": "frame_retriever",
    "metadata": {
      "source_name": "frame_179.00.png",
      "copied": true,
      "media_type": "image",
      "size_bytes": 94958
    }
  },
  {
    "artifact_id": "frame_180.00",
    "kind": "frame",
    "relpath": "artifacts/91ub3om9Fg0/frames/frame_180.00.png",
    "media_type": "image",
    "source_tool": "frame_retriever",
    "metadata": {
      "source_name": "frame_180.00.png",
      "copied": true,
      "media_type": "image",
      "size_bytes": 122921
    }
  },
  {
    "artifact_id": "frame_181.00",
    "kind": "frame",
    "relpath": "artifacts/91ub3om9Fg0/frames/frame_181.00.png",
    "media_type": "image",
    "source_tool": "frame_retriever",
    "metadata": {
      "source_name": "frame_181.00.png",
      "copied": true,
      "media_type": "image",
      "size_bytes": 179676
    }
  },
  {
    "artifact_id": "frame_182.00",
    "kind": "frame",
    "relpath": "artifacts/91ub3om9Fg0/frames/frame_182.00.png",
    "media_type": "image",
    "source_tool": "frame_retriever",
    "metadata": {
      "source_name": "frame_182.00.png",
      "copied": true,
      "media_type": "image",
      "size_bytes": 188803
    }
  },
  {
    "artifact_id": "frame_183.00",
    "kind": "frame",
    "relpath": "artifacts/91ub3om9Fg0/frames/frame_183.00.png",
    "media_type": "image",
    "source_tool": "frame_retriever",
    "metadata": {
      "source_name": "frame_183.00.png",
      "copied": true,
      "media_type": "image",
      "size_bytes": 220331
    }
  }
]
