{
  "tool_name": "frame_retriever",
  "clips": [
    {
      "video_id": "-AY84ybskqI",
      "start_s": 120.0,
      "end_s": 128.0,
      "artifact_id": null,
      "relpath": null,
      "metadata": {
        "reason": "Previously grounded relevant volunteering/drill segment with woman in gray at Inner City Tennis"
      }
    }
  ],
  "time_hints": [
    "sample across the full 120.0s-128.0s clip",
    "include early, middle, and late moments of the drill",
    "prioritize frames where the woman in gray changes lateral position or releases/tosses a ball"
  ],
  "query": "woman in gray instructor at Inner City Tennis performing the drill; frames showing lateral side-step positions and ball toss moments",
  "num_frames": 16
}
