{
  "strategy": "Directly ground the end-of-third-quarter scoreboard visually near the known 120–126s anchor, then read the score text from the retrieved frame(s).",
  "use_summary": true,
  "steps": [
    {
      "step_id": 1,
      "tool_name": "visual_temporal_grounder",
      "purpose": "Localize the clip showing the end of the third quarter scoreboard / buzzer sequence.",
      "arguments": {
        "query": "end of the third quarter scoreboard shown after a buzzer-beater in the basketball game",
        "top_k": 3
      },
      "input_refs": [],
      "depends_on": []
    },
    {
      "step_id": 2,
      "tool_name": "frame_retriever",
      "purpose": "Retrieve the most relevant frames within the localized clip that clearly show the scoreboard at the end of the third quarter.",
      "arguments": {
        "clips": [],
        "num_frames": 4,
        "query": "scoreboard showing the score and quarter at the end of the third quarter",
        "time_hints": [
          "near the final seconds of the third quarter",
          "scoreboard visible with period and clock"
        ]
      },
      "input_refs": [
        {
          "target_field": "clips",
          "source": {
            "step_id": 1,
            "field_path": "clips"
          }
        }
      ],
      "depends_on": [
        1
      ]
    },
    {
      "step_id": 3,
      "tool_name": "ocr",
      "purpose": "Read the scoreboard text from the retrieved frames to determine the score at the end of the third quarter.",
      "arguments": {
        "clips": [],
        "frames": [],
        "query": "scoreboard text including both team scores, game clock, and quarter",
        "regions": []
      },
      "input_refs": [
        {
          "target_field": "frames",
          "source": {
            "step_id": 2,
            "field_path": "frames"
          }
        }
      ],
      "depends_on": [
        2
      ]
    }
  ],
  "refinement_instructions": "Use the new evidence only to resolve the answer-critical field: the scoreboard score at the end of the third quarter. Prefer OCR-read scoreboard text from the retrieved end-of-quarter frames. The preprocess anchor around 120–126s and transcript mention of a buzzer-beater at the end of period three are useful for localization, but they are not final proof by themselves. Match the OCR score to the answer options and identify which team is leading based on the scoreboard ordering or labels if visible. If the retrieved frames do not clearly show both scores and the quarter/clock context, keep the answer unresolved rather than inferring from commentary."
}
